ordered_startup_supervisord.py
ordered_startup_supervisord-1.0.3.dist-info/DESCRIPTION.rst
ordered_startup_supervisord-1.0.3.dist-info/METADATA
ordered_startup_supervisord-1.0.3.dist-info/RECORD
ordered_startup_supervisord-1.0.3.dist-info/WHEEL
ordered_startup_supervisord-1.0.3.dist-info/entry_points.txt
ordered_startup_supervisord-1.0.3.dist-info/metadata.json
ordered_startup_supervisord-1.0.3.dist-info/top_level.txt
