Metadata-Version: 2.0
Name: ordered-startup-supervisord
Version: 1.0.3
Summary: An event listener for supervisord that will start up items in order upon certain states.
Home-page: http://github.com/jasoncorbett/ordered-startup-supervisord
Author: Jason Corbett
Author-email: UNKNOWN
License: Apache Software License v2
Platform: UNKNOWN
Classifier: License :: OSI Approved :: Apache Software License
Classifier: Programming Language :: Python :: 2.7
Classifier: Topic :: System :: Boot :: Init
Classifier: Environment :: Plugins
Requires-Dist: supervisor (>=3.2.0)
